fontv/__init__.py
fontv/app.py
fontv/commandlines.py
fontv/exceptions.py
fontv/libfv.py
fontv/settings.py
fontv/utilities.py
font_v-2.1.0.dist-info/LICENSE
font_v-2.1.0.dist-info/METADATA
font_v-2.1.0.dist-info/WHEEL
font_v-2.1.0.dist-info/entry_points.txt
font_v-2.1.0.dist-info/top_level.txt
font_v-2.1.0.dist-info/RECORD
