Metadata-Version: 2.1
Name: font-v
Version: 2.1.0
Summary: Font version reporting and modification tool
Home-page: https://github.com/source-foundry/font-v
Author: Christopher Simpkins
Author-email: chris@sourcefoundry.org
License: MIT license
Platform: any
Classifier: Development Status :: 5 - Production/Stable
Classifier: Natural Language :: English
Classifier: License :: OSI Approved :: MIT License
Classifier: Operating System :: OS Independent
Classifier: Programming Language :: Python
Classifier: Programming Language :: Python :: 3
Classifier: Programming Language :: Python :: 3.7
Classifier: Programming Language :: Python :: 3.8
Classifier: Programming Language :: Python :: 3.9
Classifier: Programming Language :: Python :: 3.10
Requires-Python: >=3.7.0
License-File: docs/LICENSE
